motion_api_client/__init__.py
motion_api_client/api_client.py
motion_api_client/models/MotionTask.py
motion_api_client/models/create_task_request.py
motion_api_client/models/update_task_request.py
motion_api_client-0.1.2.dist-info/LICENSE
motion_api_client-0.1.2.dist-info/METADATA
motion_api_client-0.1.2.dist-info/WHEEL
motion_api_client-0.1.2.dist-info/RECORD
