Metadata-Version: 2.1
Name: motion-api-client
Version: 0.1.2
Summary: 
Author: James Lund
Author-email: james.s.lund@gmail.com
Requires-Python: >=3.10,<4.0
Classifier: Programming Language :: Python :: 3
Classifier: Programming Language :: Python :: 3.10
Classifier: Programming Language :: Python :: 3.11
Requires-Dist: requests (>=2.31.0,<3.0.0)
